Workbook
Name c_prog: CHECKLIST!$D$6
Name lst_bancos: LISTAS!$A$2:$A$51
Name lst_benef: LISTAS!$G$2:$G$6
Name lst_categorias: LISTAS!$C$2:$C$13
Name lst_simnao: LISTAS!$I$2:$I$3
Name lst_status: LISTAS!$H$2:$H$4
Name lst_tipofiscal: LISTAS!$D$2:$D$13
Name lst_tiposded: LISTAS!$F$2:$F$6
Name p_ano: AJUSTES!$D$8
Name p_ded_dep: AJUSTES!$D$12
Name p_lim_edu: AJUSTES!$D$13
Name p_limite_bens: AJUSTES!$D$11
Name p_limite_isento: AJUSTES!$D$10
Name p_limite_trib: AJUSTES!$D$9
Name p_pgbl_pct: AJUSTES!$D$16
Name p_simpl_max: AJUSTES!$D$15
Name p_simpl_pct: AJUSTES!$D$14
Name r_exclusivo: RESUMO!$D$10
Name r_isento: RESUMO!$D$9
Name r_modelo: RESUMO!$D$28
Name r_obrigado: RESUMO!$D$20
Name r_trib: RESUMO!$D$8

Sheet INÍCIO
A2: LION APP | C2: ="Painel IRPF · ano-calendário "&p_ano -> Painel IRPF · ano-calendário 2025
C3: =IF(TITULAR!D7="","Preencha a aba TITULAR",TITULAR!D7&" · CPF "&TEXT(TITULAR!D8,"000\.000\.000\-00")) -> SEU MADRUGA · CPF 529.982.247-25
C5: SALDO EM BANCOS | F5: ENTRADAS NO ANO | I5: RENDIMENTOS TRIBUTÁVEIS | L5: DEDUÇÕES (MELHOR MODELO)
C6: =INFORMES!E17 -> 665000 | F6: =NOTAS!E6 -> 41650 | I6: =r_trib -> 36000 | L6: =MAX(DEDUÇÕES!L15,RESUMO!E24) -> 12561.5
C7: =COUNTA(INFORMES!D9:D16)&" instituição(ões)" -> 3 instituição(ões) | F7: =COUNT(NOTAS!F9:F208)&" lançamentos" -> 16 lançamentos | I7: =TEXT(IF(p_limite_trib=0,0,r_trib/p_limite_trib),"0%")&" do limite de obrigatoriedade" -> 101% do limite de obrigatoriedade | L7: ="Modelo sugerido: "&r_modelo -> Modelo sugerido: COMPLETA
C9: SITUAÇÃO NO IRPF | F9: CADASTRO DO TITULAR | I9: INFORMES COMPLETOS | L9: CHECKLIST CONCLUÍDO
C10: =IF(LEFT(r_obrigado,1)="O","OBRIGADO A DECLARAR","NÃO OBRIGADO") -> OBRIGADO A DECLARAR | F10: =TITULAR!D23 -> 1 | I10: =SUMPRODUCT(--(LEFT(INFORMES!I9:I16,1)="✔"))&" de "&COUNTA(INFORMES!D9:D16) -> 3 de 3 | L10: =c_prog -> 0.14285714
A11: =HYPERLINK("#'INÍCIO'!A1"," INÍCIO") -> INÍCIO
A12: =HYPERLINK("#'TITULAR'!A1"," TITULAR") -> TITULAR
A13: =HYPERLINK("#'INFORMES'!A1"," INFORMES") -> INFORMES
A14: =HYPERLINK("#'NOTAS'!A1"," NOTAS") -> NOTAS
A15: =HYPERLINK("#'DEDUÇÕES'!A1"," DEDUÇÕES") -> DEDUÇÕES
A16: =HYPERLINK("#'RESUMO'!A1"," RESUMO") -> RESUMO
A17: =HYPERLINK("#'CHECKLIST'!A1"," CHECKLIST") -> CHECKLIST
A18: =HYPERLINK("#'AJUSTES'!A1"," AJUSTES") -> AJUSTES
A21: SYSTEM IRPF
A22: v1.0 · IRPF

Sheet TITULAR
A2: LION APP
C3: 1. DADOS DO TITULAR
C4: preencha os dados da sua pessoa física abaixo
C5: Amarelo: você preenche | D5: Cinza: automático
C7: NOME | D7: SEU MADRUGA | E7: =IF(D7="","⚠ obrigatório",IF(LEN(D7)<3,"✖ nome muito curto","✔")) -> ✔
C8: CPF | D8: 52998224725 | E8: =IF(D8="","⚠ obrigatório",IF(OR(NOT(ISNUMBER(D8)),LEN(G8)<>11,G8=REPT(LEFT(G8,1),11)),"✖ CPF inválido",IF(AND(MOD(MOD(SUMPRODUCT(--MID(G8,{1,2,3,4,5,6,7,8,9},1),{10,9,8,7,6,5,4,3,2})*10,11),10)=VALUE(MID(G8,10,1)),MOD(MOD(SUMPRODUCT(--MID(G8,{1,2,3,4,5,6,7,8,9,10},1),{11,10,9,8,7,6,5,4,3,2})*10,11),10)=VALUE(MID(G8,11,1))),"✔ CPF válido","✖ CPF inválido (dígito verificador)"))) -> ✔ CPF válido | G8: =IF(D8="","",TEXT(D8,"00000000000")) -> 52998224725
C9: NASCIMENTO | D9: 25569 | E9: =IF(D9="","⚠ obrigatório",IF(NOT(ISNUMBER(D9)),"✖ data inválida",IF(D9>TODAY(),"✖ data no futuro","✔ "&INT((TODAY()-D9)/365.25)&" anos"))) -> ✔ 56 anos
C10: TÍTULO DE ELEITOR | D10: 123456789012 | E10: =IF(D10="","⚠ obrigatório",IF(AND(LEN(D10)=12,ISNUMBER(VALUE(D10))),"✔","✖ deve ter 12 dígitos")) -> ✔
A11: =HYPERLINK("#'INÍCIO'!A1"," INÍCIO") -> INÍCIO | C11: CÔNJUGE | D11: BRUXA DO 71
A12: =HYPERLINK("#'TITULAR'!A1"," TITULAR") -> TITULAR | C12: RUA | D12: BECO DA VILA, 14 | E12: =IF(D12="","⚠ obrigatório","✔") -> ✔
A13: =HYPERLINK("#'INFORMES'!A1"," INFORMES") -> INFORMES | C13: RUA ABREVIADA | D13: BCO DA VILA, 14
A14: =HYPERLINK("#'NOTAS'!A1"," NOTAS") -> NOTAS | C14: CEP | D14: 96740000 | E14: =IF(D14="","⚠ obrigatório",IF(AND(ISNUMBER(D14),D14>=1000000,D14<=99999999),"✔","✖ CEP inválido")) -> ✔
A15: =HYPERLINK("#'DEDUÇÕES'!A1"," DEDUÇÕES") -> DEDUÇÕES | C15: TELEFONE | D15: 1112345678 | E15: =IF(D15="","⚠ obrigatório",IF(AND(ISNUMBER(D15),LEN(D15)=10),"✔","✖ use DDD + 8 dígitos")) -> ✔
A16: =HYPERLINK("#'RESUMO'!A1"," RESUMO") -> RESUMO | C16: CELULAR | D16: 11912345678 | E16: =IF(D16="","⚠ obrigatório",IF(AND(ISNUMBER(D16),LEN(D16)=11),"✔","✖ use DDD + 9 dígitos")) -> ✔
A17: =HYPERLINK("#'CHECKLIST'!A1"," CHECKLIST") -> CHECKLIST | C17: E-MAIL | D17: madruguinha@gmail.com | E17: =IF(D17="","⚠ obrigatório",IF(AND(ISNUMBER(FIND("@",D17)),ISNUMBER(FIND(".",D17,FIND("@",D17)))),HYPERLINK("mailto:"&D17,"✔ clique para enviar e-mail de teste"),"✖ e-mail inválido")) -> ✔ clique para enviar e-mail de teste
A18: =HYPERLINK("#'AJUSTES'!A1"," AJUSTES") -> AJUSTES | C18: HOUVE ALTERAÇÃO DA ENTREGA ANTERIOR | D18: NÃO | E18: =IF(D18="","⚠ escolha SIM ou NÃO","✔") -> ✔
C19: DEPENDENTE CÔNJUGE | D19: NÃO | E19: =IF(D19="","⚠ escolha SIM ou NÃO","✔") -> ✔
C20: RESIDENTE NO EXTERIOR | D20: NÃO | E20: =IF(D20="","⚠ escolha SIM ou NÃO","✔") -> ✔
A21: SYSTEM IRPF | C21: Nº DE OUTROS DEPENDENTES (filhos, pais...) | D21: 0 | E21: =IF(D21="","⚠ informe 0 se não houver","✔ total de dependentes: "&((D19="SIM")+D21)) -> ✔ total de dependentes: 0
A22: v1.0 · IRPF
C23: PREENCHIMENTO DO CADASTRO | D23: =COUNTA(D7:D10,D12,D14:D21)/13 -> 1

Sheet INFORMES
A2: LION APP
C3: 2. INFORMES DE RENDIMENTOS BANCÁRIOS
C4: valor atual (saldo/rendimento em 31/12) de cada instituição · coloque os PDFs na pasta /anexos ao lado do arquivo
D5: Amarelo: você preenche | E5: Cinza: automático
C8: Nº | D8: BANCO | E8: VALOR ATUAL (R$) | F8: ANEXO (arquivo) | G8: LINK | H8: % DO TOTAL | I8: STATUS
C9: 1 | D9: 1 - Banco do Brasil | E9: 200000 | F9: bb_2025.pdf | G9: =IF(F9="","",HYPERLINK("anexos/"&F9,"📎 abrir")) -> 📎 abrir | H9: =IF(OR(E9="",$E$17=0),"",E9/$E$17) -> 0.30075188 | I9: =IF(AND(D9="",E9="",F9=""),"",IF(D9="","⚠ escolha o banco",IF(E9="","⚠ informe o valor",IF(F9="","⚠ falta anexo",IF(COUNTIF($D$9:$D$16,D9)>1,"✖ banco repetido","✔ completo"))))) -> ✔ completo
C10: 2 | D10: 184 - Banco Itaú BBA S.A. | E10: 315000 | F10: itau_2025.pdf | G10: =IF(F10="","",HYPERLINK("anexos/"&F10,"📎 abrir")) -> 📎 abrir | H10: =IF(OR(E10="",$E$17=0),"",E10/$E$17) -> 0.47368421 | I10: =IF(AND(D10="",E10="",F10=""),"",IF(D10="","⚠ escolha o banco",IF(E10="","⚠ informe o valor",IF(F10="","⚠ falta anexo",IF(COUNTIF($D$9:$D$16,D10)>1,"✖ banco repetido","✔ completo"))))) -> ✔ completo
A11: =HYPERLINK("#'INÍCIO'!A1"," INÍCIO") -> INÍCIO | C11: 3 | D11: 208 - Banco BTG Pactual | E11: 150000 | F11: btg_2025.pdf | G11: =IF(F11="","",HYPERLINK("anexos/"&F11,"📎 abrir")) -> 📎 abrir | H11: =IF(OR(E11="",$E$17=0),"",E11/$E$17) -> 0.22556391 | I11: =IF(AND(D11="",E11="",F11=""),"",IF(D11="","⚠ escolha o banco",IF(E11="","⚠ informe o valor",IF(F11="","⚠ falta anexo",IF(COUNTIF($D$9:$D$16,D11)>1,"✖ banco repetido","✔ completo"))))) -> ✔ completo
A12: =HYPERLINK("#'TITULAR'!A1"," TITULAR") -> TITULAR | C12: 4 | G12: =IF(F12="","",HYPERLINK("anexos/"&F12,"📎 abrir")) | H12: =IF(OR(E12="",$E$17=0),"",E12/$E$17) | I12: =IF(AND(D12="",E12="",F12=""),"",IF(D12="","⚠ escolha o banco",IF(E12="","⚠ informe o valor",IF(F12="","⚠ falta anexo",IF(COUNTIF($D$9:$D$16,D12)>1,"✖ banco repetido","✔ completo")))))
A13: =HYPERLINK("#'INFORMES'!A1"," INFORMES") -> INFORMES | C13: 5 | G13: =IF(F13="","",HYPERLINK("anexos/"&F13,"📎 abrir")) | H13: =IF(OR(E13="",$E$17=0),"",E13/$E$17) | I13: =IF(AND(D13="",E13="",F13=""),"",IF(D13="","⚠ escolha o banco",IF(E13="","⚠ informe o valor",IF(F13="","⚠ falta anexo",IF(COUNTIF($D$9:$D$16,D13)>1,"✖ banco repetido","✔ completo")))))
A14: =HYPERLINK("#'NOTAS'!A1"," NOTAS") -> NOTAS | C14: 6 | G14: =IF(F14="","",HYPERLINK("anexos/"&F14,"📎 abrir")) | H14: =IF(OR(E14="",$E$17=0),"",E14/$E$17) | I14: =IF(AND(D14="",E14="",F14=""),"",IF(D14="","⚠ escolha o banco",IF(E14="","⚠ informe o valor",IF(F14="","⚠ falta anexo",IF(COUNTIF($D$9:$D$16,D14)>1,"✖ banco repetido","✔ completo")))))
A15: =HYPERLINK("#'DEDUÇÕES'!A1"," DEDUÇÕES") -> DEDUÇÕES | C15: 7 | G15: =IF(F15="","",HYPERLINK("anexos/"&F15,"📎 abrir")) | H15: =IF(OR(E15="",$E$17=0),"",E15/$E$17) | I15: =IF(AND(D15="",E15="",F15=""),"",IF(D15="","⚠ escolha o banco",IF(E15="","⚠ informe o valor",IF(F15="","⚠ falta anexo",IF(COUNTIF($D$9:$D$16,D15)>1,"✖ banco repetido","✔ completo")))))
A16: =HYPERLINK("#'RESUMO'!A1"," RESUMO") -> RESUMO | C16: 8 | G16: =IF(F16="","",HYPERLINK("anexos/"&F16,"📎 abrir")) | H16: =IF(OR(E16="",$E$17=0),"",E16/$E$17) | I16: =IF(AND(D16="",E16="",F16=""),"",IF(D16="","⚠ escolha o banco",IF(E16="","⚠ informe o valor",IF(F16="","⚠ falta anexo",IF(COUNTIF($D$9:$D$16,D16)>1,"✖ banco repetido","✔ completo")))))
A17: =HYPERLINK("#'CHECKLIST'!A1"," CHECKLIST") -> CHECKLIST | D17: TOTAL | E17: =SUM(E9:E16) -> 665000 | H17: =SUM(H9:H16) -> 1
A18: =HYPERLINK("#'AJUSTES'!A1"," AJUSTES") -> AJUSTES
D19: O link 📎 abre o arquivo da pasta /anexos (mesma pasta da planilha). Máximo de 8 instituições.
A21: SYSTEM IRPF
A22: v1.0 · IRPF

Sheet NOTAS
A2: LION APP
C3: 3. NOTAS BANCÁRIAS OU EXTRATO DE HOLERITES
C4: todos os valores de entrada mês a mês (receitas) do ano-calendário
D5: Amarelo: você preenche | E5: Cinza: automático
D6: TOTAL DE ENTRADAS | E6: =SUM(F9:F208) -> 41650 | F6: =COUNT(F9:F208)&" lançamentos" -> 16 lançamentos
C8: DATA | D8: CATEGORIA | E8: DESCRIÇÃO | F8: VALOR | G8: TIPO FISCAL | H8: MÊS
C9: 45685 | D9: HOLERITE (SALÁRIO) | E9: Salário mensal | F9: 3000 | G9: =IF(D9="","",IFERROR(INDEX(lst_tipofiscal,MATCH(D9,lst_categorias,0)),"Tributável")) -> Tributável | H9: =IF(C9="","",MONTH(C9)) -> 1
C10: 45716 | D10: HOLERITE (SALÁRIO) | E10: Salário mensal | F10: 3000 | G10: =IF(D10="","",IFERROR(INDEX(lst_tipofiscal,MATCH(D10,lst_categorias,0)),"Tributável")) -> Tributável | H10: =IF(C10="","",MONTH(C10)) -> 2
A11: =HYPERLINK("#'INÍCIO'!A1"," INÍCIO") -> INÍCIO | C11: 45744 | D11: HOLERITE (SALÁRIO) | E11: Salário mensal | F11: 3000 | G11: =IF(D11="","",IFERROR(INDEX(lst_tipofiscal,MATCH(D11,lst_categorias,0)),"Tributável")) -> Tributável | H11: =IF(C11="","",MONTH(C11)) -> 3
A12: =HYPERLINK("#'TITULAR'!A1"," TITULAR") -> TITULAR | C12: 45775 | D12: HOLERITE (SALÁRIO) | E12: Salário mensal | F12: 3000 | G12: =IF(D12="","",IFERROR(INDEX(lst_tipofiscal,MATCH(D12,lst_categorias,0)),"Tributável")) -> Tributável | H12: =IF(C12="","",MONTH(C12)) -> 4
A13: =HYPERLINK("#'INFORMES'!A1"," INFORMES") -> INFORMES | C13: 45805 | D13: HOLERITE (SALÁRIO) | E13: Salário mensal | F13: 3000 | G13: =IF(D13="","",IFERROR(INDEX(lst_tipofiscal,MATCH(D13,lst_categorias,0)),"Tributável")) -> Tributável | H13: =IF(C13="","",MONTH(C13)) -> 5
A14: =HYPERLINK("#'NOTAS'!A1"," NOTAS") -> NOTAS | C14: 45836 | D14: HOLERITE (SALÁRIO) | E14: Salário mensal | F14: 3000 | G14: =IF(D14="","",IFERROR(INDEX(lst_tipofiscal,MATCH(D14,lst_categorias,0)),"Tributável")) -> Tributável | H14: =IF(C14="","",MONTH(C14)) -> 6
A15: =HYPERLINK("#'DEDUÇÕES'!A1"," DEDUÇÕES") -> DEDUÇÕES | C15: 45866 | D15: HOLERITE (SALÁRIO) | E15: Salário mensal | F15: 3000 | G15: =IF(D15="","",IFERROR(INDEX(lst_tipofiscal,MATCH(D15,lst_categorias,0)),"Tributável")) -> Tributável | H15: =IF(C15="","",MONTH(C15)) -> 7
A16: =HYPERLINK("#'RESUMO'!A1"," RESUMO") -> RESUMO | C16: 45897 | D16: HOLERITE (SALÁRIO) | E16: Salário mensal | F16: 3000 | G16: =IF(D16="","",IFERROR(INDEX(lst_tipofiscal,MATCH(D16,lst_categorias,0)),"Tributável")) -> Tributável | H16: =IF(C16="","",MONTH(C16)) -> 8
A17: =HYPERLINK("#'CHECKLIST'!A1"," CHECKLIST") -> CHECKLIST | C17: 45928 | D17: HOLERITE (SALÁRIO) | E17: Salário mensal | F17: 3000 | G17: =IF(D17="","",IFERROR(INDEX(lst_tipofiscal,MATCH(D17,lst_categorias,0)),"Tributável")) -> Tributável | H17: =IF(C17="","",MONTH(C17)) -> 9
A18: =HYPERLINK("#'AJUSTES'!A1"," AJUSTES") -> AJUSTES | C18: 45958 | D18: HOLERITE (SALÁRIO) | E18: Salário mensal | F18: 3000 | G18: =IF(D18="","",IFERROR(INDEX(lst_tipofiscal,MATCH(D18,lst_categorias,0)),"Tributável")) -> Tributável | H18: =IF(C18="","",MONTH(C18)) -> 10
C19: 45989 | D19: HOLERITE (SALÁRIO) | E19: Salário mensal | F19: 3000 | G19: =IF(D19="","",IFERROR(INDEX(lst_tipofiscal,MATCH(D19,lst_categorias,0)),"Tributável")) -> Tributável | H19: =IF(C19="","",MONTH(C19)) -> 11
C20: 46019 | D20: HOLERITE (SALÁRIO) | E20: Salário mensal | F20: 3000 | G20: =IF(D20="","",IFERROR(INDEX(lst_tipofiscal,MATCH(D20,lst_categorias,0)),"Tributável")) -> Tributável | H20: =IF(C20="","",MONTH(C20)) -> 12
A21: SYSTEM IRPF | C21: 46011 | D21: 13º SALÁRIO | E21: 13º salário | F21: 3000 | G21: =IF(D21="","",IFERROR(INDEX(lst_tipofiscal,MATCH(D21,lst_categorias,0)),"Tributável")) -> Exclusivo na fonte | H21: =IF(C21="","",MONTH(C21)) -> 12
A22: v1.0 · IRPF | C22: 45838 | D22: RENDA FIXA (CDB/TESOURO) | E22: CDB BTG | F22: 1250 | G22: =IF(D22="","",IFERROR(INDEX(lst_tipofiscal,MATCH(D22,lst_categorias,0)),"Tributável")) -> Exclusivo na fonte | H22: =IF(C22="","",MONTH(C22)) -> 6
C23: 45915 | D23: DIVIDENDOS | E23: Dividendos de ações | F23: 480 | G23: =IF(D23="","",IFERROR(INDEX(lst_tipofiscal,MATCH(D23,lst_categorias,0)),"Tributável")) -> Isento / não tributável | H23: =IF(C23="","",MONTH(C23)) -> 9
C24: 46022 | D24: POUPANÇA / LCI / LCA | E24: LCI Itaú | F24: 920 | G24: =IF(D24="","",IFERROR(INDEX(lst_tipofiscal,MATCH(D24,lst_categorias,0)),"Tributável")) -> Isento / não tributável | H24: =IF(C24="","",MONTH(C24)) -> 12
G25: =IF(D25="","",IFERROR(INDEX(lst_tipofiscal,MATCH(D25,lst_categorias,0)),"Tributável")) | H25: =IF(C25="","",MONTH(C25))
G26: =IF(D26="","",IFERROR(INDEX(lst_tipofiscal,MATCH(D26,lst_categorias,0)),"Tributável")) | H26: =IF(C26="","",MONTH(C26))
G27: =IF(D27="","",IFERROR(INDEX(lst_tipofiscal,MATCH(D27,lst_categorias,0)),"Tributável")) | H27: =IF(C27="","",MONTH(C27))
G28: =IF(D28="","",IFERROR(INDEX(lst_tipofiscal,MATCH(D28,lst_categorias,0)),"Tributável")) | H28: =IF(C28="","",MONTH(C28))
G29: =IF(D29="","",IFERROR(INDEX(lst_tipofiscal,MATCH(D29,lst_categorias,0)),"Tributável")) | H29: =IF(C29="","",MONTH(C29))
G30: =IF(D30="","",IFERROR(INDEX(lst_tipofiscal,MATCH(D30,lst_categorias,0)),"Tributável")) | H30: =IF(C30="","",MONTH(C30))
G31: =IF(D31="","",IFERROR(INDEX(lst_tipofiscal,MATCH(D31,lst_categorias,0)),"Tributável")) | H31: =IF(C31="","",MONTH(C31))
G32: =IF(D32="","",IFERROR(INDEX(lst_tipofiscal,MATCH(D32,lst_categorias,0)),"Tributável")) | H32: =IF(C32="","",MONTH(C32))
G33: =IF(D33="","",IFERROR(INDEX(lst_tipofiscal,MATCH(D33,lst_categorias,0)),"Tributável")) | H33: =IF(C33="","",MONTH(C33))
G34: =IF(D34="","",IFERROR(INDEX(lst_tipofiscal,MATCH(D34,lst_categorias,0)),"Tributável")) | H34: =IF(C34="","",MONTH(C34))
G35: =IF(D35="","",IFERROR(INDEX(lst_tipofiscal,MATCH(D35,lst_categorias,0)),"Tributável")) | H35: =IF(C35="","",MONTH(C35))
G36: =IF(D36="","",IFERROR(INDEX(lst_tipofiscal,MATCH(D36,lst_categorias,0)),"Tributável")) | H36: =IF(C36="","",MONTH(C36))
... G208: =IF(D208="","",IFERROR(INDEX(lst_tipofiscal,MATCH(D208,lst_categorias,0)),"Tributável")) | H208: =IF(C208="","",MONTH(C208))

Sheet DEDUÇÕES
A2: LION APP
C3: 4. DESPESAS DEDUTÍVEIS
C4: saúde, educação, previdência e pensão · limites aplicados automaticamente (aba AJUSTES)
D5: Amarelo: você preenche | E5: Cinza: automático
C8: DATA | D8: TIPO | E8: BENEFICIÁRIO | F8: PRESTADOR | G8: CPF/CNPJ | H8: VALOR | J8: TIPO | K8: INFORMADO (R$) | L8: DEDUTÍVEL (R$)
C9: 45726 | D9: Saúde | E9: Titular | F9: Clínica Vila Saudável | G9: 12345678000190 | H9: 1200 | J9: Saúde | K9: =SUMIFS($H$9:$H$108,$D$9:$D$108,J9) -> 6600 | L9: =K9 -> 6600
C10: 46022 | D10: Saúde | E10: Titular | F10: Plano de saúde (anual) | G10: 98765432000110 | H10: 5400 | J10: Educação | K10: =SUMIFS($H$9:$H$108,$D$9:$D$108,J10) -> 4200 | L10: =SUM(L20:L24) -> 3561.5
A11: =HYPERLINK("#'INÍCIO'!A1"," INÍCIO") -> INÍCIO | C11: 45874 | D11: Educação | E11: Titular | F11: Faculdade (anuidade) | G11: 11222333000144 | H11: 4200 | J11: Previdência privada (PGBL) | K11: =SUMIFS($H$9:$H$108,$D$9:$D$108,J11) -> 2400 | L11: =MIN(K11,p_pgbl_pct*r_trib) -> 2400
A12: =HYPERLINK("#'TITULAR'!A1"," TITULAR") -> TITULAR | C12: 46022 | D12: Previdência privada (PGBL) | E12: Titular | F12: Fundo PGBL | G12: 55666777000188 | H12: 2400 | J12: Previdência oficial (INSS) | K12: =SUMIFS($H$9:$H$108,$D$9:$D$108,J12) -> 0 | L12: =K12 -> 0
A13: =HYPERLINK("#'INFORMES'!A1"," INFORMES") -> INFORMES | J13: Pensão alimentícia | K13: =SUMIFS($H$9:$H$108,$D$9:$D$108,J13) -> 0 | L13: =K13 -> 0
A14: =HYPERLINK("#'NOTAS'!A1"," NOTAS") -> NOTAS | J14: Dependentes (qtd × dedução) | K14: =(TITULAR!D19="SIM")+TITULAR!D21 -> 0 | L14: =K14*p_ded_dep -> 0
A15: =HYPERLINK("#'DEDUÇÕES'!A1"," DEDUÇÕES") -> DEDUÇÕES | J15: TOTAL | K15: =SUM(K9:K13) -> 13200 | L15: =SUM(L9:L14) -> 12561.5
A16: =HYPERLINK("#'RESUMO'!A1"," RESUMO") -> RESUMO | J16: PGBL limitado a 12% dos rendimentos tributáveis; educação limitada por pessoa.
A17: =HYPERLINK("#'CHECKLIST'!A1"," CHECKLIST") -> CHECKLIST
A18: =HYPERLINK("#'AJUSTES'!A1"," AJUSTES") -> AJUSTES
J19: EDUCAÇÃO POR PESSOA | K19: INFORMADO (R$) | L19: DEDUTÍVEL (R$)
J20: Titular | K20: =SUMIFS($H$9:$H$108,$D$9:$D$108,"Educação",$E$9:$E$108,J20) -> 4200 | L20: =MIN(K20,p_lim_edu) -> 3561.5
A21: SYSTEM IRPF | J21: Cônjuge | K21: =SUMIFS($H$9:$H$108,$D$9:$D$108,"Educação",$E$9:$E$108,J21) -> 0 | L21: =MIN(K21,p_lim_edu) -> 0
A22: v1.0 · IRPF | J22: Dependente 1 | K22: =SUMIFS($H$9:$H$108,$D$9:$D$108,"Educação",$E$9:$E$108,J22) -> 0 | L22: =MIN(K22,p_lim_edu) -> 0
J23: Dependente 2 | K23: =SUMIFS($H$9:$H$108,$D$9:$D$108,"Educação",$E$9:$E$108,J23) -> 0 | L23: =MIN(K23,p_lim_edu) -> 0
J24: Dependente 3 | K24: =SUMIFS($H$9:$H$108,$D$9:$D$108,"Educação",$E$9:$E$108,J24) -> 0 | L24: =MIN(K24,p_lim_edu) -> 0

Sheet RESUMO
A2: LION APP
C3: 5. RESUMO FISCAL E SIMULAÇÃO
C4: obrigatoriedade de declarar e comparação entre declaração completa e simplificada
C5: Amarelo: você preenche | D5: Cinza: automático
C7: RENDIMENTOS DO ANO-CALENDÁRIO | D7: VALOR (R$) | E7: FICHA NO PROGRAMA IRPF
C8: Rendimentos tributáveis | D8: =SUMIF(NOTAS!$G$9:$G$208,"Tributável",NOTAS!$F$9:$F$208) -> 36000 | E8: Rendimentos Tributáveis Recebidos de PJ / PF
C9: Rendimentos isentos e não tributáveis | D9: =SUMIF(NOTAS!$G$9:$G$208,"Isento / não tributável",NOTAS!$F$9:$F$208) -> 1400 | E9: Rendimentos Isentos e Não Tributáveis
C10: Rendimentos exclusivos na fonte | D10: =SUMIF(NOTAS!$G$9:$G$208,"Exclusivo na fonte",NOTAS!$F$9:$F$208) -> 4250 | E10: Rendimentos Sujeitos à Tributação Exclusiva/Definitiva
A11: =HYPERLINK("#'INÍCIO'!A1"," INÍCIO") -> INÍCIO | C11: TOTAL DE RENDIMENTOS | D11: =SUM(D8:D10) -> 41650
A12: =HYPERLINK("#'TITULAR'!A1"," TITULAR") -> TITULAR | C12: Saldo bancário informado (Bens e Direitos) | D12: =INFORMES!E17 -> 665000 | E12: Bens e Direitos · código 06 (depósitos à vista)
A13: =HYPERLINK("#'INFORMES'!A1"," INFORMES") -> INFORMES
A14: =HYPERLINK("#'NOTAS'!A1"," NOTAS") -> NOTAS | C14: OBRIGATORIEDADE (critérios) | D14: SEU VALOR | E14: LIMITE | F14: ATINGIDO?
A15: =HYPERLINK("#'DEDUÇÕES'!A1"," DEDUÇÕES") -> DEDUÇÕES | C15: Rendimentos tributáveis acima do limite | D15: =r_trib -> 36000 | E15: =p_limite_trib -> 35584 | F15: =IF(D15>E15,"SIM","NÃO") -> SIM
A16: =HYPERLINK("#'RESUMO'!A1"," RESUMO") -> RESUMO | C16: Isentos + exclusivos na fonte acima do limite | D16: =r_isento+r_exclusivo -> 5650 | E16: =p_limite_isento -> 200000 | F16: =IF(D16>E16,"SIM","NÃO") -> NÃO
A17: =HYPERLINK("#'CHECKLIST'!A1"," CHECKLIST") -> CHECKLIST | C17: Bens e direitos em 31/12 acima do limite | D17: =D12 -> 665000 | E17: =p_limite_bens -> 800000 | F17: =IF(D17>E17,"SIM","NÃO") -> NÃO
A18: =HYPERLINK("#'AJUSTES'!A1"," AJUSTES") -> AJUSTES | C18: Teve ganho de capital / operações em bolsa? | D18: NÃO | E18: — | F18: =IF(D18="SIM","SIM","NÃO") -> NÃO
C19: Outra condição (rural, exterior...)? | D19: NÃO | E19: — | F19: =IF(OR(D19="SIM",TITULAR!D20="SIM"),"SIM","NÃO") -> NÃO
C20: RESULTADO | D20: =IF(COUNTIF(F15:F19,"SIM")>0,"OBRIGADO A DECLARAR","NÃO OBRIGADO (confirme)") -> OBRIGADO A DECLARAR
A21: SYSTEM IRPF
A22: v1.0 · IRPF | C22: SIMULAÇÃO: COMPLETA x SIMPLIFICADA | D22: COMPLETA | E22: SIMPLIFICADA
C23: Rendimentos tributáveis | D23: =r_trib -> 36000 | E23: =r_trib -> 36000
C24: (−) Deduções | D24: =DEDUÇÕES!L15 -> 12561.5 | E24: =MIN(p_simpl_pct*r_trib,p_simpl_max) -> 7200
C25: Base de cálculo do imposto | D25: =MAX(0,D23-D24) -> 23438.5 | E25: =MAX(0,E23-E24) -> 28800
C26: Vantagem do modelo escolhido (redução de base) | D26: =ABS(D24-E24) -> 5361.5
C28: MODELO MAIS VANTAJOSO | D28: =IF(D24>E24,"COMPLETA","SIMPLIFICADA") -> COMPLETA
C30: Atenção: a simulação compara apenas a redução da base de cálculo. O imposto final depende da tabela progressiva e do imposto retido; confirme no programa oficial da Receita Federal antes de transmitir.

Sheet CHECKLIST
A2: LION APP
C3: 6. CHECKLIST DA DECLARAÇÃO
C4: acompanhe cada etapa até a transmissão · links oficiais ao lado
D5: Amarelo: você preenche | E5: Cinza: automático
D6: =COUNTIF(G9:G22,"Concluído")/COUNTA(D9:D22) -> 0.14285714 | E6: ← progresso geral das etapas
C8: Nº | D8: ETAPA / DOCUMENTO | E8: ONDE OBTER | F8: LINK | G8: STATUS | H8: OBSERVAÇÕES
C9: 1 | D9: Informe de rendimentos do empregador (holerites) | E9: Departamento pessoal / portal do RH | G9: Concluído
C10: 2 | D10: Informes de rendimentos de todos os bancos | E10: App ou site de cada banco | G10: Concluído
A11: =HYPERLINK("#'INÍCIO'!A1"," INÍCIO") -> INÍCIO | C11: 3 | D11: Lista de bancos onde você tem conta | E11: Registrato (Banco Central) | F11: =HYPERLINK("https://www.bcb.gov.br/meubc/registrato","🔗 abrir site") -> 🔗 abrir site | G11: Em andamento
A12: =HYPERLINK("#'TITULAR'!A1"," TITULAR") -> TITULAR | C12: 4 | D12: Extrato consolidado de ações, FIIs e ETFs | E12: Área do Investidor B3 | F12: =HYPERLINK("https://www.investidor.b3.com.br","🔗 abrir site") -> 🔗 abrir site | G12: Pendente
A13: =HYPERLINK("#'INFORMES'!A1"," INFORMES") -> INFORMES | C13: 5 | D13: Notas de corretagem e DARFs de bolsa | E13: Corretora | G13: Pendente
A14: =HYPERLINK("#'NOTAS'!A1"," NOTAS") -> NOTAS | C14: 6 | D14: Recibos de despesas médicas (com CPF/CNPJ) | E14: Clínicas, planos, dentistas | G14: Pendente
A15: =HYPERLINK("#'DEDUÇÕES'!A1"," DEDUÇÕES") -> DEDUÇÕES | C15: 7 | D15: Comprovantes de educação | E15: Escola / faculdade | G15: Pendente
A16: =HYPERLINK("#'RESUMO'!A1"," RESUMO") -> RESUMO | C16: 8 | D16: Comprovante de PGBL / previdência | E16: Seguradora / banco | G16: Pendente
A17: =HYPERLINK("#'CHECKLIST'!A1"," CHECKLIST") -> CHECKLIST | C17: 9 | D17: Dados dos dependentes (CPF e nascimento) | E17: Documentos pessoais | G17: Pendente
A18: =HYPERLINK("#'AJUSTES'!A1"," AJUSTES") -> AJUSTES | C18: 10 | D18: Bens e direitos: imóveis, veículos, saldos em 31/12 | E18: Escrituras, CRLV, extratos | G18: Pendente
C19: 11 | D19: Dívidas e ônus reais | E19: Contratos e financiamentos | G19: Pendente
C20: 12 | D20: Conferir pendências e declaração pré-preenchida | E20: e-CAC (Receita Federal) | F20: =HYPERLINK("https://cav.receita.fazenda.gov.br/autenticacao/login","🔗 abrir site") -> 🔗 abrir site | G20: Pendente
A21: SYSTEM IRPF | C21: 13 | D21: Transmitir a declaração | E21: Programa IRPF / app Meu Imposto de Renda | F21: =HYPERLINK("https://www.gov.br/receitafederal/pt-br/assuntos/meu-imposto-de-renda","🔗 abrir site") -> 🔗 abrir site | G21: Pendente
A22: v1.0 · IRPF | C22: 14 | D22: Arquivar o recibo e os documentos por 5 anos | E22: Pasta digital organizada por ano | G22: Pendente

Sheet AJUSTES
A2: LION APP
C3: 7. AJUSTES E PARÂMETROS
C4: valores usados nos cálculos · atualize a cada ano-calendário
C7: PARÂMETRO | D7: VALOR | E7: FONTE / OBSERVAÇÃO
C8: Ano-calendário | D8: 2025 | E8: Declaração entregue em 2026 refere-se ao ano-calendário 2025. Valor definido pelo autor.
C9: Limite de rendimentos tributáveis (obrigatoriedade) | D9: 35584 | E9: Fonte: Calculacentro, 'Imposto de Renda 2026 – guia' (calculacentro.com/blog/imposto-de-renda-2026-guia). Alguns sites ainda citam R$ 33.888,00 (ano anterior): confirme no gov.br.
C10: Limite de rendimentos isentos / exclusivos na fonte | D10: 200000 | E10: Fonte: Calculacentro, 'Imposto de Renda 2026 – guia' (calculacentro.com/blog/imposto-de-renda-2026-guia).
A11: =HYPERLINK("#'INÍCIO'!A1"," INÍCIO") -> INÍCIO | C11: Limite de bens e direitos em 31/12 | D11: 800000 | E11: Critério de obrigatoriedade da Receita Federal (valor recordado pelo autor; confirme no gov.br).
A12: =HYPERLINK("#'TITULAR'!A1"," TITULAR") -> TITULAR | C12: Dedução por dependente (anual) | D12: 2275.08 | E12: Fonte: Qive, 'IRPF 2026: guia completo' (qive.com.br/blog/irpf-2026-guia-completo).
A13: =HYPERLINK("#'INFORMES'!A1"," INFORMES") -> INFORMES | C13: Limite de dedução com educação (por pessoa/ano) | D13: 3561.5 | E13: Fonte: Qive, 'IRPF 2026: guia completo' (qive.com.br/blog/irpf-2026-guia-completo).
A14: =HYPERLINK("#'NOTAS'!A1"," NOTAS") -> NOTAS | C14: Desconto simplificado (% dos rendimentos tributáveis) | D14: 0.2 | E14: Fonte: Calculacentro, 'Imposto de Renda 2026 – guia' (calculacentro.com/blog/imposto-de-renda-2026-guia).
A15: =HYPERLINK("#'DEDUÇÕES'!A1"," DEDUÇÕES") -> DEDUÇÕES | C15: Teto do desconto simplificado | D15: 17640 | E15: Fonte: Qive, 'IRPF 2026: guia completo' (qive.com.br/blog/irpf-2026-guia-completo); Calculacentro, 'Imposto de Renda 2026 – guia' (calculacentro.com/blog/imposto-de-renda-2026-guia).
A16: =HYPERLINK("#'RESUMO'!A1"," RESUMO") -> RESUMO | C16: Limite de dedução do PGBL (% dos rendimentos tributáveis) | D16: 0.12 | E16: Lei 9.250/1995, art. 11 (valor recordado pelo autor; confirme no gov.br).
A17: =HYPERLINK("#'CHECKLIST'!A1"," CHECKLIST") -> CHECKLIST
A18: =HYPERLINK("#'AJUSTES'!A1"," AJUSTES") -> AJUSTES | C18: As listas (bancos, categorias, tipos de dedução) ficam na aba oculta LISTAS: clique com o botão direito em uma aba > Reexibir.
C19: Novas regras de isenção até R$ 5.000/mês valem para rendimentos a partir de 2026 e não alteram a declaração do ano-calendário 2025.
A21: SYSTEM IRPF
A22: v1.0 · IRPF

Sheet LISTAS
A1: bancos | C1: categorias | D1: tipo_fiscal | F1: tipos_deducao | G1: beneficiarios | H1: status | I1: sim_nao | J1: tipos_fiscais
A2: 1 - Banco do Brasil | C2: HOLERITE (SALÁRIO) | D2: Tributável | F2: Saúde | G2: Titular | H2: Pendente | I2: SIM | J2: Tributável
A3: 3 - Banco da Amazônia | C3: PRÓ-LABORE | D3: Tributável | F3: Educação | G3: Cônjuge | H3: Em andamento | I3: NÃO | J3: Isento / não tributável
A4: 4 - Banco do Nordeste do Brasil | C4: ALUGUEL | D4: Tributável | F4: Previdência privada (PGBL) | G4: Dependente 1 | H4: Concluído | J4: Exclusivo na fonte
A5: 24 - Banco de Pernambuco | C5: AUTÔNOMO / FREELANCE | D5: Tributável | F5: Previdência oficial (INSS) | G5: Dependente 2
A6: 29 - Banco do Estado do Rio de Janeiro | C6: 13º SALÁRIO | D6: Exclusivo na fonte | F6: Pensão alimentícia | G6: Dependente 3
A7: 33 - Banco Santander | C7: RENDA FIXA (CDB/TESOURO) | D7: Exclusivo na fonte
A8: 37 - Banco do Estado do Pará | C8: JCP | D8: Exclusivo na fonte
A9: 41 - Banco do Estado do Rio Grande do Sul | C9: DIVIDENDOS | D9: Isento / não tributável
A10: 44 - Banco BVA | C10: POUPANÇA / LCI / LCA | D10: Isento / não tributável
A11: 62 - Hipercard Banco Múltiplo | C11: FGTS / INDENIZAÇÃO | D11: Isento / não tributável
A12: 65 - Banco Lemon | C12: DOAÇÃO / HERANÇA | D12: Isento / não tributável
A13: 66 - Banco Morgan Stanley | C13: OUTROS | D13: Tributável
A14: 72 - Banco Rural Mais
A15: 74 - Banco J. Safra
A16: 77 - Banco Inter
A17: 79 - Banco JBS
A18: 82 - Banco Topázio
A19: 102 - XP Investimentos CCTVM S.A.
A20: 104 - Caixa Econômica Federal
A21: 119 - Banco Western Union do Brasil
A22: 184 - Banco Itaú BBA S.A.
A23: 197 - Stone Pagamentos
A24: 208 - Banco BTG Pactual
A25: 212 - Banco Original
... A51: 749 - Banco Simples

Sheet CALC
A1: mes | B1: n | C1: Entradas (R$) | E1: Tipo fiscal | F1: Valor (R$)
A2: Jan | B2: 1 | C2: =SUMIFS(NOTAS!$F$9:$F$208,NOTAS!$H$9:$H$208,B2) -> 3000 | E2: Tributável | F2: =SUMIF(NOTAS!$G$9:$G$208,E2,NOTAS!$F$9:$F$208) -> 36000
A3: Fev | B3: 2 | C3: =SUMIFS(NOTAS!$F$9:$F$208,NOTAS!$H$9:$H$208,B3) -> 3000 | E3: Isento / não tributável | F3: =SUMIF(NOTAS!$G$9:$G$208,E3,NOTAS!$F$9:$F$208) -> 1400
A4: Mar | B4: 3 | C4: =SUMIFS(NOTAS!$F$9:$F$208,NOTAS!$H$9:$H$208,B4) -> 3000 | E4: Exclusivo na fonte | F4: =SUMIF(NOTAS!$G$9:$G$208,E4,NOTAS!$F$9:$F$208) -> 4250
A5: Abr | B5: 4 | C5: =SUMIFS(NOTAS!$F$9:$F$208,NOTAS!$H$9:$H$208,B5) -> 3000
A6: Mai | B6: 5 | C6: =SUMIFS(NOTAS!$F$9:$F$208,NOTAS!$H$9:$H$208,B6) -> 3000
A7: Jun | B7: 6 | C7: =SUMIFS(NOTAS!$F$9:$F$208,NOTAS!$H$9:$H$208,B7) -> 4250
A8: Jul | B8: 7 | C8: =SUMIFS(NOTAS!$F$9:$F$208,NOTAS!$H$9:$H$208,B8) -> 3000
A9: Ago | B9: 8 | C9: =SUMIFS(NOTAS!$F$9:$F$208,NOTAS!$H$9:$H$208,B9) -> 3000
A10: Set | B10: 9 | C10: =SUMIFS(NOTAS!$F$9:$F$208,NOTAS!$H$9:$H$208,B10) -> 3480
A11: Out | B11: 10 | C11: =SUMIFS(NOTAS!$F$9:$F$208,NOTAS!$H$9:$H$208,B11) -> 3000
A12: Nov | B12: 11 | C12: =SUMIFS(NOTAS!$F$9:$F$208,NOTAS!$H$9:$H$208,B12) -> 3000
A13: Dez | B13: 12 | C13: =SUMIFS(NOTAS!$F$9:$F$208,NOTAS!$H$9:$H$208,B13) -> 6920
